__init__.py
configs/__init__.py
configs/gitignore.py
configs/mainapp.py
configs/others.py
configs/settings.py
create/__init__.py
create/create_core.py
create/create_dj.py
create/create_gitignore.py
create/create_others.py
create/create_settings.py
idealDjango-0.0.1.dist-info/LICENSE
idealDjango-0.0.1.dist-info/METADATA
idealDjango-0.0.1.dist-info/WHEEL
idealDjango-0.0.1.dist-info/top_level.txt
idealDjango-0.0.1.dist-info/RECORD
