Metadata-Version: 2.1
Name: idealDjango
Version: 0.0.1
Summary: an ideal template for Django projects
Author-email: Amir Shahsafi <meshahsafi@gmail.com>
License: MIT License        
Project-URL: Homepage, https://github.com/mrShahsafi/ideal-django/tree/package
Project-URL: Bug Tracker, https://github.com/mrShahsafi/ideal-django/tree/package/issues
Classifier: Programming Language :: Python :: 3
Classifier: License :: OSI Approved :: MIT License
Classifier: Operating System :: OS Independent
Requires-Python: >=3.7
License-File: LICENSE
